amatak_shop/forms/__init__.py
amatak_shop/forms/checkout.py
amatak_shop/forms/coupon.py
amatak_shop/forms/payment.py
amatak_shop/forms/payment_choices.py
amatak_shop/forms/refund.py
amatak_shop/management/commands/rename.py
amatak_shop/migrations/0001_initial.py
amatak_shop/migrations/__init__.py
amatak_shop/models/__init__.py
amatak_shop/models/address.py
amatak_shop/models/category.py
amatak_shop/models/coupon.py
amatak_shop/models/item.py
amatak_shop/models/mixins.py
amatak_shop/models/order.py
amatak_shop/models/order_item.py
amatak_shop/models/payment.py
amatak_shop/models/refund.py
amatak_shop/models/user_profile.py
amatak_shop/models/user_receiver_profile.py
amatak_shop/settings/__init__.py
amatak_shop/settings/base.py
amatak_shop/static/amatak_shop/bulma/LICENSE
amatak_shop/static/amatak_shop/bulma/README.md
amatak_shop/static/amatak_shop/bulma/bulma.sass
amatak_shop/static/amatak_shop/bulma/package.json
amatak_shop/static/amatak_shop/bulma/css/bulma-rtl.css
amatak_shop/static/amatak_shop/bulma/css/bulma-rtl.css.map
amatak_shop/static/amatak_shop/bulma/css/bulma-rtl.min.css
amatak_shop/static/amatak_shop/bulma/css/bulma.css
amatak_shop/static/amatak_shop/bulma/css/bulma.css.map
amatak_shop/static/amatak_shop/bulma/css/bulma.min.css
amatak_shop/static/amatak_shop/bulma/sass/base/_all.sass
amatak_shop/static/amatak_shop/bulma/sass/base/animations.sass
amatak_shop/static/amatak_shop/bulma/sass/base/generic.sass
amatak_shop/static/amatak_shop/bulma/sass/base/helpers.sass
amatak_shop/static/amatak_shop/bulma/sass/base/minireset.sass
amatak_shop/static/amatak_shop/bulma/sass/components/_all.sass
amatak_shop/static/amatak_shop/bulma/sass/components/breadcrumb.sass
amatak_shop/static/amatak_shop/bulma/sass/components/card.sass
amatak_shop/static/amatak_shop/bulma/sass/components/dropdown.sass
amatak_shop/static/amatak_shop/bulma/sass/components/level.sass
amatak_shop/static/amatak_shop/bulma/sass/components/media.sass
amatak_shop-1.1.0.dist-info/METADATA
amatak_shop-1.1.0.dist-info/WHEEL
amatak_shop-1.1.0.dist-info/top_level.txt
amatak_shop-1.1.0.dist-info/RECORD
