Metadata-Version: 2.1
Name: amatak-shop
Version: 1.1.0
Summary: Amatak OpenSource Online Shop 
Author-email: Rony MAN <amatak.io@outlook.com>
Project-URL: Homepage, https://github.com/amatak-org/AmatakOnlineShop
Project-URL: Bug Tracker, https://github.com/amatak-org/AmatakOnlineShop/issues
Classifier: Programming Language :: Python :: 3
Classifier: License :: OSI Approved :: MIT License
Classifier: Operating System :: OS Independent
Requires-Python: >=3.7
